src/__init__.py
src/addone.py
src/__pycache__/__init__.cpython-310.pyc
src/__pycache__/addone.cpython-310.pyc
lastonewillwork-0.1.3.dist-info/METADATA
lastonewillwork-0.1.3.dist-info/WHEEL
lastonewillwork-0.1.3.dist-info/entry_points.txt
lastonewillwork-0.1.3.dist-info/top_level.txt
lastonewillwork-0.1.3.dist-info/RECORD
