Metadata-Version: 2.1
Name: lastonewillwork
Version: 0.1.3
Summary: Test CICD
Home-page: https://gitlab.com/hachshara/CICD
Author: Guy
Author-email: guykishon1@gmail.com
License: UNKNOWN
Platform: UNKNOWN
Classifier: Programming Language :: Python :: 3.11
